{
  "__inputs": [],
  "__elements": {},
  "__requires": [
    {
      "type": "datasource",
      "id": "cloudwatch",
      "name": "CloudWatch",
      "version": "1.0.0"
    },
    {
      "type": "grafana",
      "id": "grafana",
      "name": "Grafana",
      "version": "10.1.5"
    },
    {
      "type": "datasource",
      "id": "influxdb",
      "name": "InfluxDB",
      "version": "1.0.0"
    },
    {
      "type": "panel",
      "id": "text",
      "name": "Text",
      "version": ""
    },
    {
      "type": "panel",
      "id": "timeseries",
      "name": "Time series",
      "version": ""
    }
  ],
  "annotations": {
    "list": [
      {
        "builtIn": 1,
        "datasource": {
          "type": "datasource",
          "uid": "grafana"
        },
        "enable": true,
        "hide": true,
        "iconColor": "rgba(0, 211, 255, 1)",
        "name": "Annotations & Alerts",
        "type": "dashboard"
      }
    ]
  },
  "description": "Visualize AWS Kinesis Data Firehose metrics",
  "editable": false,
  "fiscalYearStartMonth": 0,
  "graphTooltip": 0,
  "id": null,
  "links": [],
  "liveNow": false,
  "panels": [
    {
      "collapsed": false,
      "gridPos": {
        "h": 1,
        "w": 24,
        "x": 0,
        "y": 0
      },
      "id": 5,
      "panels": [],
      "title": "Data Ingestion Through Direct PUT",
      "type": "row"
    },
    {
      "datasource": {
        "type": "cloudwatch",
        "uid": "$datasource"
      },
      "fieldConfig": {
        "defaults": {
          "color": {
            "mode": "palette-classic"
          },
          "custom": {
            "axisCenteredZero": false,
            "axisColorMode": "text",
            "axisLabel": "",
            "axisPlacement": "auto",
            "barAlignment": 0,
            "drawStyle": "line",
            "fillOpacity": 10,
            "gradientMode": "none",
            "hideFrom": {
              "legend": false,
              "tooltip": false,
              "viz": false
            },
            "insertNulls": false,
            "lineInterpolation": "linear",
            "lineWidth": 1,
            "pointSize": 5,
            "scaleDistribution": {
              "type": "linear"
            },
            "showPoints": "never",
            "spanNulls": false,
            "stacking": {
              "group": "A",
              "mode": "none"
            },
            "thresholdsStyle": {
              "mode": "off"
            }
          },
          "links": [],
          "mappings": [],
          "min": 0,
          "thresholds": {
            "mode": "absolute",
            "steps": [
              {
                "color": "green",
                "value": null
              },
              {
                "color": "red",
                "value": 80
              }
            ]
          },
          "unit": "short"
        },
        "overrides": [
          {
            "matcher": {
              "id": "byName",
              "options": "Maximum"
            },
            "properties": [
              {
                "id": "color",
                "value": {
                  "fixedColor": "#e24d42",
                  "mode": "fixed"
                }
              }
            ]
          },
          {
            "matcher": {
              "id": "byName",
              "options": "IncomingBytes Sum"
            },
            "properties": [
              {
                "id": "unit",
                "value": "bytes"
              }
            ]
          }
        ]
      },
      "gridPos": {
        "h": 7,
        "w": 24,
        "x": 0,
        "y": 1
      },
      "id": 1,
      "links": [],
      "options": {
        "legend": {
          "calcs": [
            "mean",
            "lastNotNull",
            "max",
            "min",
            "sum"
          ],
          "displayMode": "table",
          "placement": "bottom",
          "showLegend": true
        },
        "tooltip": {
          "mode": "multi",
          "sort": "none"
        }
      },
      "pluginVersion": "10.1.5",
      "targets": [
        {
          "alias": "{{metric}} {{stat}}",
          "application": {
            "filter": ""
          },
          "datasource": {
            "uid": "$datasource"
          },
          "dimensions": {
            "DeliveryStreamName": "$deliverystreamname"
          },
          "expression": "",
          "functions": [],
          "group": {
            "filter": ""
          },
          "highResolution": false,
          "host": {
            "filter": ""
          },
          "id": "",
          "item": {
            "filter": ""
          },
          "label": "${PROP('MetricName')} ${PROP('Stat')}",
          "matchExact": true,
          "metricEditorMode": 0,
          "metricName": "IncomingRecords",
          "metricQueryType": 0,
          "mode": 0,
          "namespace": "AWS/Firehose",
          "options": {
            "showDisabledItems": false
          },
          "period": "$agg",
          "refId": "A",
          "region": "$region",
          "returnData": false,
          "statistic": "Sum"
        },
        {
          "alias": "{{metric}} {{stat}}",
          "application": {
            "filter": ""
          },
          "datasource": {
            "uid": "$datasource"
          },
          "dimensions": {
            "DeliveryStreamName": "$deliverystreamname"
          },
          "expression": "",
          "functions": [],
          "group": {
            "filter": ""
          },
          "highResolution": false,
          "host": {
            "filter": ""
          },
          "id": "",
          "item": {
            "filter": ""
          },
          "label": "${PROP('MetricName')} ${PROP('Stat')}",
          "matchExact": true,
          "metricEditorMode": 0,
          "metricName": "IncomingBytes",
          "metricQueryType": 0,
          "mode": 0,
          "namespace": "AWS/Firehose",
          "options": {
            "showDisabledItems": false
          },
          "period": "$agg",
          "refId": "B",
          "region": "$region",
          "returnData": false,
          "statistic": "Sum"
        }
      ],
      "title": "IncomingRecords/IncomingBytes",
      "type": "timeseries"
    },
    {
      "datasource": {
        "type": "cloudwatch",
        "uid": "$datasource"
      },
      "fieldConfig": {
        "defaults": {
          "color": {
            "mode": "palette-classic"
          },
          "custom": {
            "axisCenteredZero": false,
            "axisColorMode": "text",
            "axisLabel": "",
            "axisPlacement": "auto",
            "barAlignment": 0,
            "drawStyle": "line",
            "fillOpacity": 10,
            "gradientMode": "none",
            "hideFrom": {
              "legend": false,
              "tooltip": false,
              "viz": false
            },
            "insertNulls": false,
            "lineInterpolation": "linear",
            "lineWidth": 1,
            "pointSize": 5,
            "scaleDistribution": {
              "type": "linear"
            },
            "showPoints": "never",
            "spanNulls": false,
            "stacking": {
              "group": "A",
              "mode": "none"
            },
            "thresholdsStyle": {
              "mode": "off"
            }
          },
          "links": [],
          "mappings": [],
          "min": 0,
          "thresholds": {
            "mode": "absolute",
            "steps": [
              {
                "color": "green",
                "value": null
              },
              {
                "color": "red",
                "value": 80
              }
            ]
          },
          "unit": "reqps"
        },
        "overrides": [
          {
            "matcher": {
              "id": "byName",
              "options": "ThrottledRecords Average"
            },
            "properties": [
              {
                "id": "unit",
                "value": "none"
              },
              {
                "id": "custom.axisPlacement",
                "value": "right"
              }
            ]
          }
        ]
      },
      "gridPos": {
        "h": 7,
        "w": 24,
        "x": 0,
        "y": 8
      },
      "id": 4,
      "links": [],
      "options": {
        "legend": {
          "calcs": [
            "mean",
            "lastNotNull",
            "max",
            "min",
            "sum"
          ],
          "displayMode": "table",
          "placement": "bottom",
          "showLegend": true
        },
        "tooltip": {
          "mode": "multi",
          "sort": "none"
        }
      },
      "pluginVersion": "10.1.5",
      "targets": [
        {
          "alias": "{{metric}} {{stat}}",
          "application": {
            "filter": ""
          },
          "datasource": {
            "uid": "$datasource"
          },
          "dimensions": {
            "DeliveryStreamName": "$deliverystreamname"
          },
          "expression": "",
          "functions": [],
          "group": {
            "filter": ""
          },
          "highResolution": false,
          "host": {
            "filter": ""
          },
          "id": "",
          "item": {
            "filter": ""
          },
          "label": "${PROP('MetricName')} ${PROP('Stat')}",
          "matchExact": true,
          "metricEditorMode": 0,
          "metricName": "RecordsPerSecondLimit",
          "metricQueryType": 0,
          "mode": 0,
          "namespace": "AWS/Firehose",
          "options": {
            "showDisabledItems": false
          },
          "period": "$agg",
          "refId": "A",
          "region": "$region",
          "returnData": false,
          "statistic": "Average"
        },
        {
          "alias": "{{metric}} {{stat}}",
          "application": {
            "filter": ""
          },
          "datasource": {
            "uid": "$datasource"
          },
          "dimensions": {
            "DeliveryStreamName": "$deliverystreamname"
          },
          "expression": "",
          "functions": [],
          "group": {
            "filter": ""
          },
          "highResolution": false,
          "host": {
            "filter": ""
          },
          "id": "",
          "item": {
            "filter": ""
          },
          "label": "${PROP('MetricName')} ${PROP('Stat')}",
          "matchExact": true,
          "metricEditorMode": 0,
          "metricName": "ThrottledRecords",
          "metricQueryType": 0,
          "mode": 0,
          "namespace": "AWS/Firehose",
          "options": {
            "showDisabledItems": false
          },
          "period": "$agg",
          "refId": "B",
          "region": "$region",
          "returnData": false,
          "statistic": "Average"
        }
      ],
      "title": "RecordsPerSecondLimit/ThrottledRecords",
      "type": "timeseries"
    },
    {
      "collapsed": false,
      "gridPos": {
        "h": 1,
        "w": 24,
        "x": 0,
        "y": 15
      },
      "id": 6,
      "panels": [],
      "title": "Delivery to Splunk",
      "type": "row"
    },
    {
      "datasource": {
        "type": "cloudwatch",
        "uid": "$datasource"
      },
      "fieldConfig": {
        "defaults": {
          "color": {
            "mode": "palette-classic"
          },
          "custom": {
            "axisCenteredZero": false,
            "axisColorMode": "text",
            "axisLabel": "",
            "axisPlacement": "auto",
            "barAlignment": 0,
            "drawStyle": "line",
            "fillOpacity": 10,
            "gradientMode": "none",
            "hideFrom": {
              "legend": false,
              "tooltip": false,
              "viz": false
            },
            "insertNulls": false,
            "lineInterpolation": "linear",
            "lineWidth": 1,
            "pointSize": 5,
            "scaleDistribution": {
              "type": "linear"
            },
            "showPoints": "never",
            "spanNulls": false,
            "stacking": {
              "group": "A",
              "mode": "none"
            },
            "thresholdsStyle": {
              "mode": "off"
            }
          },
          "links": [],
          "mappings": [],
          "min": 0,
          "thresholds": {
            "mode": "absolute",
            "steps": [
              {
                "color": "green",
                "value": null
              },
              {
                "color": "red",
                "value": 80
              }
            ]
          },
          "unit": "none"
        },
        "overrides": [
          {
            "matcher": {
              "id": "byName",
              "options": "DeliveryToSplunk.Bytes Sum"
            },
            "properties": [
              {
                "id": "unit",
                "value": "bytes"
              },
              {
                "id": "custom.axisPlacement",
                "value": "right"
              }
            ]
          }
        ]
      },
      "gridPos": {
        "h": 7,
        "w": 24,
        "x": 0,
        "y": 16
      },
      "id": 7,
      "links": [],
      "options": {
        "legend": {
          "calcs": [
            "mean",
            "lastNotNull",
            "max",
            "min",
            "sum"
          ],
          "displayMode": "table",
          "placement": "bottom",
          "showLegend": true
        },
        "tooltip": {
          "mode": "multi",
          "sort": "none"
        }
      },
      "pluginVersion": "10.1.5",
      "targets": [
        {
          "alias": "{{metric}} {{stat}}",
          "application": {
            "filter": ""
          },
          "datasource": {
            "uid": "$datasource"
          },
          "dimensions": {
            "DeliveryStreamName": "$deliverystreamname"
          },
          "expression": "",
          "functions": [],
          "group": {
            "filter": ""
          },
          "highResolution": false,
          "host": {
            "filter": ""
          },
          "id": "",
          "item": {
            "filter": ""
          },
          "label": "${PROP('MetricName')} ${PROP('Stat')}",
          "matchExact": true,
          "metricEditorMode": 0,
          "metricName": "DeliveryToSplunk.Records",
          "metricQueryType": 0,
          "mode": 0,
          "namespace": "AWS/Firehose",
          "options": {
            "showDisabledItems": false
          },
          "period": "$agg",
          "refId": "A",
          "region": "$region",
          "returnData": false,
          "statistic": "Average"
        },
        {
          "alias": "{{metric}} {{stat}}",
          "application": {
            "filter": ""
          },
          "datasource": {
            "uid": "$datasource"
          },
          "dimensions": {
            "DeliveryStreamName": "$deliverystreamname"
          },
          "expression": "",
          "functions": [],
          "group": {
            "filter": ""
          },
          "highResolution": false,
          "host": {
            "filter": ""
          },
          "id": "",
          "item": {
            "filter": ""
          },
          "label": "${PROP('MetricName')} ${PROP('Stat')}",
          "matchExact": true,
          "metricEditorMode": 0,
          "metricName": "DeliveryToSplunk.Bytes",
          "metricQueryType": 0,
          "mode": 0,
          "namespace": "AWS/Firehose",
          "options": {
            "showDisabledItems": false
          },
          "period": "$agg",
          "refId": "B",
          "region": "$region",
          "returnData": false,
          "statistic": "Sum"
        }
      ],
      "title": "DeliveryToSplunk.Records/DeliveryToSplunk.Bytes",
      "type": "timeseries"
    },
    {
      "datasource": {
        "type": "cloudwatch",
        "uid": "$datasource"
      },
      "fieldConfig": {
        "defaults": {
          "color": {
            "mode": "palette-classic"
          },
          "custom": {
            "axisCenteredZero": false,
            "axisColorMode": "text",
            "axisLabel": "",
            "axisPlacement": "auto",
            "barAlignment": 0,
            "drawStyle": "line",
            "fillOpacity": 10,
            "gradientMode": "none",
            "hideFrom": {
              "legend": false,
              "tooltip": false,
              "viz": false
            },
            "insertNulls": false,
            "lineInterpolation": "linear",
            "lineWidth": 1,
            "pointSize": 5,
            "scaleDistribution": {
              "type": "linear"
            },
            "showPoints": "never",
            "spanNulls": false,
            "stacking": {
              "group": "A",
              "mode": "none"
            },
            "thresholdsStyle": {
              "mode": "off"
            }
          },
          "links": [],
          "mappings": [],
          "min": 0,
          "thresholds": {
            "mode": "absolute",
            "steps": [
              {
                "color": "green",
                "value": null
              },
              {
                "color": "red",
                "value": 80
              }
            ]
          },
          "unit": "none"
        },
        "overrides": [
          {
            "matcher": {
              "id": "byName",
              "options": "DeliveryToSplunk.DataFreshness Average"
            },
            "properties": [
              {
                "id": "unit",
                "value": "s"
              },
              {
                "id": "custom.axisPlacement",
                "value": "right"
              }
            ]
          }
        ]
      },
      "gridPos": {
        "h": 7,
        "w": 24,
        "x": 0,
        "y": 23
      },
      "id": 9,
      "links": [],
      "options": {
        "legend": {
          "calcs": [
            "mean",
            "lastNotNull",
            "max",
            "min",
            "sum"
          ],
          "displayMode": "table",
          "placement": "bottom",
          "showLegend": true
        },
        "tooltip": {
          "mode": "multi",
          "sort": "none"
        }
      },
      "pluginVersion": "10.1.5",
      "targets": [
        {
          "alias": "{{metric}} {{stat}}",
          "application": {
            "filter": ""
          },
          "datasource": {
            "uid": "$datasource"
          },
          "dimensions": {
            "DeliveryStreamName": "$deliverystreamname"
          },
          "expression": "",
          "functions": [],
          "group": {
            "filter": ""
          },
          "highResolution": false,
          "host": {
            "filter": ""
          },
          "id": "",
          "item": {
            "filter": ""
          },
          "label": "${PROP('MetricName')} ${PROP('Stat')}",
          "matchExact": true,
          "metricEditorMode": 0,
          "metricName": "DeliveryToSplunk.Success",
          "metricQueryType": 0,
          "mode": 0,
          "namespace": "AWS/Firehose",
          "options": {
            "showDisabledItems": false
          },
          "period": "$agg",
          "refId": "A",
          "region": "$region",
          "returnData": false,
          "statistic": "SampleCount"
        },
        {
          "alias": "{{metric}} {{stat}}",
          "application": {
            "filter": ""
          },
          "datasource": {
            "uid": "$datasource"
          },
          "dimensions": {
            "DeliveryStreamName": "$deliverystreamname"
          },
          "expression": "",
          "functions": [],
          "group": {
            "filter": ""
          },
          "highResolution": false,
          "host": {
            "filter": ""
          },
          "id": "",
          "item": {
            "filter": ""
          },
          "label": "${PROP('MetricName')} ${PROP('Stat')}",
          "matchExact": true,
          "metricEditorMode": 0,
          "metricName": "DeliveryToSplunk.DataFreshness",
          "metricQueryType": 0,
          "mode": 0,
          "namespace": "AWS/Firehose",
          "options": {
            "showDisabledItems": false
          },
          "period": "$agg",
          "refId": "B",
          "region": "$region",
          "returnData": false,
          "statistic": "Average"
        }
      ],
      "title": "DeliveryToSplunk.Success/DeliveryToSplunk.DataFreshness",
      "type": "timeseries"
    },
    {
      "collapsed": false,
      "gridPos": {
        "h": 1,
        "w": 24,
        "x": 0,
        "y": 30
      },
      "id": 8,
      "panels": [],
      "type": "row"
    },
    {
      "datasource": {
        "type": "influxdb",
        "uid": "${datasource}"
      },
      "editable": true,
      "error": false,
      "gridPos": {
        "h": 3,
        "w": 24,
        "x": 0,
        "y": 31
      },
      "id": 2,
      "links": [],
      "options": {
        "code": {
          "language": "plaintext",
          "showLineNumbers": false,
          "showMiniMap": false
        },
        "content": "<a href=\"http://www.monitoringartist.com\" target=\"_blank\" title=\"Dashboard maintained by Monitoring Artist - DevOps / Docker / Kubernetes / AWS ECS / Google GCP / Zabbix / Zenoss / Terraform / Monitoring\"><img src=\"https://monitoringartist.github.io/monitoring-artist-logo-grafana.png\" height=\"30px\" /></a> | \n<a target=\"_blank\" href=\"https://docs.aws.amazon.com/streams/latest/dev/monitoring-with-cloudwatch.html\">AWS CloudWatch Kinesis documentation</a> | \n<a target=\"_blank\" href=\"https://grafana.com/dashboards/20144\">Installed from Grafana.com dashboards</a>",
        "mode": "html"
      },
      "pluginVersion": "10.1.5",
      "targets": [
        {
          "datasource": {
            "type": "influxdb",
            "uid": "${datasource}"
          },
          "refId": "A"
        }
      ],
      "title": "Documentation",
      "type": "text"
    }
  ],
  "refresh": "",
  "schemaVersion": 38,
  "style": "dark",
  "tags": [],
  "templating": {
    "list": [
      {
        "current": {},
        "hide": 0,
        "includeAll": false,
        "label": "Datasource",
        "multi": false,
        "name": "datasource",
        "options": [],
        "query": "cloudwatch",
        "queryValue": "trac",
        "refresh": 1,
        "regex": "",
        "skipUrlSync": false,
        "type": "datasource"
      },
      {
        "auto": true,
        "auto_count": 30,
        "auto_min": "10s",
        "current": {},
        "hide": 0,
        "label": "Aggregation",
        "name": "agg",
        "options": [
          {
            "selected": true,
            "text": "auto",
            "value": "$__auto_interval_agg"
          },
          {
            "selected": false,
            "text": "1s",
            "value": "1s"
          },
          {
            "selected": false,
            "text": "5s",
            "value": "5s"
          },
          {
            "selected": false,
            "text": "10s",
            "value": "10s"
          },
          {
            "selected": false,
            "text": "30s",
            "value": "30s"
          },
          {
            "selected": true,
            "text": "1m",
            "value": "1m"
          },
          {
            "selected": false,
            "text": "5m",
            "value": "5m"
          },
          {
            "selected": false,
            "text": "15m",
            "value": "15m"
          },
          {
            "selected": false,
            "text": "1h",
            "value": "1h"
          },
          {
            "selected": false,
            "text": "6h",
            "value": "6h"
          },
          {
            "selected": false,
            "text": "1d",
            "value": "1d"
          },
          {
            "selected": false,
            "text": "7d",
            "value": "7d"
          },
          {
            "selected": false,
            "text": "30d",
            "value": "30d"
          }
        ],
        "query": "1s,5s,10s,30s,1m,5m,15m,1h,6h,1d,7d,30d",
        "queryValue": "",
        "refresh": 2,
        "skipUrlSync": false,
        "type": "interval"
      },
      {
        "current": {},
        "datasource": {
          "type": "cloudwatch",
          "uid": "$datasource"
        },
        "definition": "regions()",
        "hide": 0,
        "includeAll": false,
        "label": "Region",
        "multi": false,
        "name": "region",
        "options": [],
        "query": "regions()",
        "refresh": 1,
        "regex": "",
        "skipUrlSync": false,
        "sort": 1,
        "tagValuesQuery": "",
        "tagsQuery": "",
        "type": "query",
        "useTags": false
      },
      {
        "current": {},
        "datasource": {
          "type": "cloudwatch",
          "uid": "$datasource"
        },
        "definition": "",
        "hide": 0,
        "includeAll": false,
        "label": "DeliveryStreamName",
        "multi": false,
        "name": "deliverystreamname",
        "options": [],
        "query": {
          "attributeName": "",
          "dimensionFilters": {},
          "dimensionKey": "DeliveryStreamName",
          "ec2Filters": {},
          "instanceID": "",
          "metricName": "IncomingBytes",
          "namespace": "AWS/Firehose",
          "queryType": "dimensionValues",
          "refId": "CloudWatchVariableQueryEditor-VariableQuery",
          "region": "$region",
          "resourceType": "",
          "tags": {}
        },
        "refresh": 1,
        "regex": "",
        "skipUrlSync": false,
        "sort": 1,
        "tagValuesQuery": "",
        "tagsQuery": "",
        "type": "query",
        "useTags": false
      }
    ]
  },
  "time": {
    "from": "now-12h",
    "to": "now"
  },
  "timepicker": {
    "refresh_intervals": [
      "5s",
      "10s",
      "30s",
      "1m",
      "5m",
      "15m",
      "30m",
      "1h",
      "2h",
      "1d"
    ],
    "time_options": [
      "5m",
      "15m",
      "1h",
      "6h",
      "12h",
      "24h",
      "2d",
      "7d",
      "30d"
    ]
  },
  "timezone": "browser",
  "title": "AWS Kinesis Firehose",
  "uid": "AWSFirehose",
  "version": 1,
  "weekStart": ""
}